myWebKraken_package/__init__.py
myWebKraken_package/myKrakenAPI.py
myWebKraken_package/myWebKraken.py
mywebkraken_package-0.1.4.dist-info/WHEEL
mywebkraken_package-0.1.4.dist-info/METADATA
mywebkraken_package-0.1.4.dist-info/RECORD
