Metadata-Version: 2.1
Name: mywebkraken-package
Version: 0.1.4
Summary: 
License: MIT
Author: LADM
Author-email: you@example.com
Requires-Python: >=3.10,<4.0
Classifier: License :: OSI Approved :: MIT License
Classifier: Programming Language :: Python :: 3
Classifier: Programming Language :: Python :: 3.10
Classifier: Programming Language :: Python :: 3.11
Requires-Dist: dash (>=2.6.2,<3.0.0)
Requires-Dist: pykrakenapi (>=0.3.1,<0.4.0)
